example_package_bisan/__init__.py
example_package_bisan/example.py
example_package_bisan-0.1.0.dist-info/LICENSE
example_package_bisan-0.1.0.dist-info/METADATA
example_package_bisan-0.1.0.dist-info/WHEEL
example_package_bisan-0.1.0.dist-info/entry_points.txt
example_package_bisan-0.1.0.dist-info/top_level.txt
example_package_bisan-0.1.0.dist-info/RECORD
